xia_puller_flask/__init__.py
xia_puller_flask/api.cpython-310-darwin.so
xia_puller_flask-0.0.12.dist-info/LICENSE.txt
xia_puller_flask-0.0.12.dist-info/METADATA
xia_puller_flask-0.0.12.dist-info/WHEEL
xia_puller_flask-0.0.12.dist-info/top_level.txt
xia_puller_flask-0.0.12.dist-info/RECORD
