Metadata-Version: 2.1
Name: xia-puller-flask
Version: 0.0.12
Summary: UNKNOWN
Home-page: https://develop.x-i-a.com/docs/xia-puller-flask/0.0.12/index.html
Author: X-I-A
Author-email: admin@x-i-a.com
License: UNKNOWN
Platform: UNKNOWN
Requires-Python: >=3.9
License-File: LICENSE.txt
Requires-Dist: flask
Requires-Dist: xia-puller
Requires-Dist: xia-agent-flask
